MANIFEST.in
pypi_description.txt
setup.py
adspygoogle/__init__.py
adspygoogle.egg-info/PKG-INFO
adspygoogle.egg-info/SOURCES.txt
adspygoogle.egg-info/dependency_links.txt
adspygoogle.egg-info/requires.txt
adspygoogle.egg-info/top_level.txt
adspygoogle/SOAPpy/Client.py
adspygoogle/SOAPpy/Config.py
adspygoogle/SOAPpy/Errors.py
adspygoogle/SOAPpy/NS.py
adspygoogle/SOAPpy/Parser.py
adspygoogle/SOAPpy/SOAP.py
adspygoogle/SOAPpy/SOAPBuilder.py
adspygoogle/SOAPpy/Server.py
adspygoogle/SOAPpy/Types.py
adspygoogle/SOAPpy/URLopener.py
adspygoogle/SOAPpy/Utilities.py
adspygoogle/SOAPpy/WSDL.py
adspygoogle/SOAPpy/__init__.py
adspygoogle/SOAPpy/download_and_patch_soappy.py
adspygoogle/SOAPpy/version.py
adspygoogle/SOAPpy/wstools/Namespaces.py
adspygoogle/SOAPpy/wstools/TimeoutSocket.py
adspygoogle/SOAPpy/wstools/UserTuple.py
adspygoogle/SOAPpy/wstools/Utility.py
adspygoogle/SOAPpy/wstools/WSDLTools.py
adspygoogle/SOAPpy/wstools/XMLSchema.py
adspygoogle/SOAPpy/wstools/XMLname.py
adspygoogle/SOAPpy/wstools/__init__.py
adspygoogle/SOAPpy/wstools/c14n.py
adspygoogle/SOAPpy/wstools/logging.py
adspygoogle/adwords/AdWordsClient.py
adspygoogle/adwords/AdWordsErrors.py
adspygoogle/adwords/AdWordsSanityCheck.py
adspygoogle/adwords/AdWordsSoapBuffer.py
adspygoogle/adwords/AdWordsUtils.py
adspygoogle/adwords/GenericAdWordsService.py
adspygoogle/adwords/ReportDownloader.py
adspygoogle/adwords/__init__.py
adspygoogle/adwords/data/README
adspygoogle/adwords/data/currencies.csv
adspygoogle/adwords/data/error_codes.csv
adspygoogle/adwords/data/error_types.csv
adspygoogle/adwords/data/service_types.csv
adspygoogle/adwords/data/timezones.csv
adspygoogle/adwords/util/XsdToWsdl.py
adspygoogle/adwords/util/__init__.py
adspygoogle/common/AuthToken.py
adspygoogle/common/Buffer.py
adspygoogle/common/Client.py
adspygoogle/common/Errors.py
adspygoogle/common/GenericApiService.py
adspygoogle/common/Logger.py
adspygoogle/common/MessageHandler.py
adspygoogle/common/SanityCheck.py
adspygoogle/common/SoapBuffer.py
adspygoogle/common/Utils.py
adspygoogle/common/__init__.py
adspygoogle/common/https/Https.py
adspygoogle/common/https/__init__.py
