Metadata-Version: 1.0
Name: adspygoogle
Version: 1.1.10
Summary: Google Ads Python Client Library
Home-page: https://github.com/googleads/googleads-python-legacy-lib
Author: Joseph DiLallo
Author-email: api.jdilallo@gmail.com
License: Apache License 2.0
Keywords: adwords adxbuyer dfp dfa google
Platform: any
